{
  "version": 3,
  "file": "",
  "sourceRoot": "",
  "sources": [
    ""
  ],
  "names": [],
  "mappings": "AAAA;AAAA,MAAA,gCAAA;IAAA;mSAAA;;AAAA,EAAA,OAAgB,OAAA,CAAQ,MAAR,CAAhB,EAAC,YAAA,IAAD,EAAO,aAAA,KAAP,CAAA;;AAAA,EAGM;AAEJ,oCAAA,CAAA;;;;KAAA;;AAAA,IAAA,aAAC,CAAA,OAAD,GAAU,SAAA,GAAA;aACR,IAAC,CAAA,GAAD,CAAK;AAAA,QAAA,OAAA,EAAO,6CAAP;OAAL,EAA2D,CAAA,SAAA,KAAA,GAAA;eAAA,SAAA,GAAA;iBACzD,KAAC,CAAA,EAAD,CAAI;AAAA,YAAA,OAAA,EAAO,kBAAP;AAAA,YAA2B,MAAA,EAAQ,YAAnC;WAAJ,EADyD;QAAA,EAAA;MAAA,CAAA,CAAA,CAAA,IAAA,CAA3D,EADQ;IAAA,CAAV,CAAA;;AAAA,4BAIA,IAAA,GAAM,SAAA,GAAA;AACJ,MAAA,yCAAA,SAAA,CAAA,CAAA;AAAA,MAEA,IAAC,CAAA,EAAD,CAAI,OAAJ,EAAa,OAAb,EAAsB,SAAA,GAAA;AACpB,YAAA,EAAA;AAAA,QAAA,EAAA,GAAK,IAAC,CAAA,aAAa,CAAC,sBAAf,CAAsC,eAAtC,CAAuD,CAAA,CAAA,CAA5D,CAAA;eACA,IAAI,CAAC,SAAS,CAAC,KAAf,CAAqB,EAAE,CAAC,SAAxB,EAFoB;MAAA,CAAtB,CAFA,CAAA;aAMA,IAAC,CAAA,EAAD,CAAI,OAAJ,EAAa,YAAb,EAA2B,SAAA,GAAA;AACzB,YAAA,gBAAA;AAAA,QAAA,IAAA,GAAO,QAAA,CAAS,IAAC,CAAA,OAAO,CAAC,IAAlB,EAAwB,EAAxB,CAAP,CAAA;AAAA,QACA,GAAA,GAAM,QAAA,CAAS,IAAC,CAAA,OAAO,CAAC,GAAlB,EAAuB,EAAvB,CADN,CAAA;yEAEgC,CAAE,uBAAlC,CAA8D,IAAA,KAAA,CAAM,IAAN,EAAY,GAAZ,CAA9D,WAHyB;MAAA,CAA3B,EAPI;IAAA,CAJN,CAAA;;AAAA,4BAgBA,cAAA,GAAgB,SAAC,WAAD,GAAA;AACd,UAAA,KAAA;AAAA,MAAA,IAAA,CAAA,IAAe,CAAA,aAAf;AAAA,cAAA,CAAA;OAAA;AAAA,MAEA,IAAC,CAAA,IAAD,CAAM,gBAAN,CAAuB,CAAC,WAAxB,CAAoC,qBAApC,CAFA,CAAA;AAAA,MAIA,KAAA,GAAQ,IAAC,CAAA,IAAD,CAAM,eAAA,GAAkB,WAAxB,CAJR,CAAA;6BAMA,KAAK,CAAE,QAAP,CAAgB,qBAAhB,WAPc;IAAA,CAhBhB,CAAA;;AAAA,4BAyBA,IAAA,GAAM,SAAA,GAAA;AAGJ,MAAA,IAAC,CAAA,GAAD,CAAK,OAAL,EAAc,OAAd,CAAA,CAAA;AAAA,MACA,IAAC,CAAA,GAAD,CAAK,OAAL,EAAc,YAAd,CADA,CAAA;aAEA,yCAAA,SAAA,EALI;IAAA,CAzBN,CAAA;;AAAA,4BAgCA,eAAA,GAAiB,SAAC,QAAD,EAAW,QAAX,EAAqB,WAArB,EAAkC,iBAAlC,GAAA;AAEf,UAAA,4EAAA;AAAA,MAAA,IAAC,CAAA,UAAU,CAAC,KAAZ,CAAA,CAAA,CAAA;AAGA,MAAA,IAA4C,IAAC,CAAA,aAA7C;AAAA,QAAA,QAAQ,CAAC,IAAT,CAAc,SAAC,CAAD,EAAI,CAAJ,GAAA;iBAAU,CAAC,CAAC,IAAF,GAAS,CAAC,CAAC,KAArB;QAAA,CAAd,CAAA,CAAA;OAHA;AAMA,WAAA,+DAAA;+BAAA;AAEE,QAAA,WAAA,wCAAwB,CAAE,aAAZ,CAA0B,QAA1B,WAAA,IAAwC,KAAA,IAAS,EAAjD,IAAwD,iBAAtE,CAAA;AAAA,QAEA,UAAA,wCAAuB,CAAE,KAAK,CAAC,aAAlB,KAAyB,WAAzB,IAAyC,CAAA,iBAFtD,CAAA;AAKA,QAAA,IAAG,WAAA,IAAe,UAAf,IAA6B,IAAC,CAAA,aAAjC;AACE,UAAA,GAAA,GAAO,QAAA,GAAQ,IAAI,CAAC,IAApB,CAAA;AACA,UAAA,IAAG,gBAAH;AAAkB,YAAA,GAAA,GAAM,EAAA,GAAG,GAAH,GAAO,UAAP,GAAiB,IAAI,CAAC,GAA5B,CAAlB;WADA;AAAA,UAEA,SAAA,GAER,iCAAA,GACe,IAAI,CAAC,KADpB,GAC0B,IAD1B,GAC8B,IAAI,CAAC,MADnC,GAC0C,uGAD1C,GAI+B,CAAC,IAAI,CAAC,IAAL,GAAY,CAAb,CAJ/B,GAI8C,cAJ9C,GAKM,CAAC,IAAI,CAAC,GAAL,GAAW,CAAX,IAAgB,CAAjB,CALN,GAKyB,iDALzB,GAKwE,CAAC,IAAI,CAAC,IAAL,GAAY,CAAb,CALxE,GAKuF,IALvF,GAK2F,IAAI,CAAC,OALhG,GAMI,iCANJ,GAMoC,GANpC,GAMwC,2BAVhC,CAAA;AAAA,UAiBA,IAAC,CAAA,UAAU,CAAC,MAAZ,CAAmB,SAAnB,CAjBA,CADF;SAPF;AAAA,OANA;AAkCA,MAAA,IAAG,iBAAH;AACE,QAAA,IAAC,CAAA,IAAD,CAAA,CAAA,CAAA;eACA,IAAC,CAAA,cAAD,CAAgB,WAAhB,EAFF;OApCe;IAAA,CAhCjB,CAAA;;AAAA,4BAyEA,MAAA,GAAQ,SAAC,QAAD,EAAW,MAAX,GAAA;AAEN,UAAA,wCAAA;AAAA,MAAA,IAAI,CAAC,aAAa,CAAC,eAAnB,CAAmC,IAAnC,CAAA,CAAA;AAAA,MAIA,iBAAA,GAAoB,IAAI,CAAC,MAAM,CAAC,GAAZ,CAAgB,8CAAhB,CAJpB,CAAA;AAAA,MAMA,IAAC,CAAA,aAAD,GAAiB,IAAI,CAAC,MAAM,CAAC,GAAZ,CAAgB,iCAAhB,CANjB,CAAA;AAAA,MASA,IAAC,CAAA,IAAD,CAAA,CATA,CAAA;AAYA,MAAA,IAAA,CAAA,CAAc,QAAQ,CAAC,MAAT,GAAkB,CAAhC,CAAA;AAAA,cAAA,CAAA;OAZA;AAcA,MAAA,IAAG,8BAAH;AAEE,QAAA,QAAA,GAAW,MAAM,CAAC,uBAAP,CAAA,CAAX,CAFF;OAAA,MAAA;AAIE,cAAA,CAJF;OAdA;AAAA,MAqBA,WAAA,GAAc,QAAQ,CAAC,GArBvB,CAAA;aAsBA,IAAC,CAAA,eAAD,CAAiB,QAAjB,EAA2B,QAA3B,EAAqC,WAArC,EAAkD,iBAAlD,EAxBM;IAAA,CAzER,CAAA;;yBAAA;;KAF0B,KAH5B,CAAA;;AAAA,EAwGA,MAAM,CAAC,OAAP,GAAiB,aAxGjB,CAAA;AAAA"
}